{"cameraMode":{"drawMode":0,"name":"Shaded","section":"Shading Mode"},"sceneLighting":false,"audioPlay":false,"sceneViewState":{"m_AlwaysRefresh":false,"showFog":true,"showSkybox":false,"showFlares":true,"showImageEffects":true,"showParticleSystems":true,"showVisualEffectGraphs":true,"m_FxEnabled":true},"in2DMode":false,"pivot":{"x":-6.0,"y":0.4938686490058899,"z":-1.9797621965408326},"rotation":{"x":-0.10142574459314347,"y":0.8321837782859802,"z":-0.16339585185050965,"w":-0.5202968716621399},"size":0.9157102704048157,"orthographic":false}